fortepyan/__init__.py
fortepyan/config.py
fortepyan/main.py
fortepyan/analytics/clustering/__init__.py
fortepyan/analytics/clustering/process.py
fortepyan/analytics/clustering/structures.py
fortepyan/analytics/clustering/views.py
fortepyan/audio/__init__.py
fortepyan/audio/render.py
fortepyan/audio/soundfont.py
fortepyan/midi/__init__.py
fortepyan/midi/structures.py
fortepyan/midi/tools.py
fortepyan/view/__init__.py
fortepyan/view/animation/__init__.py
fortepyan/view/animation/dualroll.py
fortepyan/view/animation/evolution.py
fortepyan/view/animation/main.py
fortepyan/view/animation/pianoroll.py
fortepyan/view/pianoroll/__init__.py
fortepyan/view/pianoroll/dual.py
fortepyan/view/pianoroll/main.py
fortepyan/view/pianoroll/structures.py
fortepyan-0.4.6.dist-info/METADATA
fortepyan-0.4.6.dist-info/WHEEL
fortepyan-0.4.6.dist-info/top_level.txt
fortepyan-0.4.6.dist-info/RECORD
