Metadata-Version: 2.4
Name: fortepyan
Version: 0.4.6
Summary: Process MIDI piano with (almost) no pain
Author-email: Piano For AI <roszcz+fortepyan@gmail.com>
Project-URL: Homepage, https://github.com/Nospoko/fortepyan
Keywords: midi,music,piano
Classifier: License :: OSI Approved :: MIT License
Classifier: Programming Language :: Python
Classifier: Programming Language :: Python :: 3
Requires-Python: >=3.9
Requires-Dist: appdirs>=1.4.4
Requires-Dist: pandas
Requires-Dist: midi2audio>=0.1.1
Requires-Dist: numpy>=1.23.4
Requires-Dist: pretty-midi>=0.2.9
Requires-Dist: pydub>=0.25
Requires-Dist: matplotlib>=3.6.2
Requires-Dist: Levenshtein>=0.20.9
Requires-Dist: cmcrameri>=1.5
Provides-Extra: dev
Requires-Dist: pre-commit~=3.8.0; extra == "dev"
Requires-Dist: pytest==7.4.3; extra == "dev"
Requires-Dist: pytest-watch==4.2.0; extra == "dev"
Requires-Dist: streamlit-pianoroll==0.7.1; extra == "dev"
Provides-Extra: test
Requires-Dist: pytest~=8.0.0; extra == "test"
Requires-Dist: pytest-watch==4.2.0; extra == "test"
